threatbus_inmem/__init__.py
threatbus_inmem/plugin.py
threatbus_inmem-2022.5.16.dist-info/METADATA
threatbus_inmem-2022.5.16.dist-info/WHEEL
threatbus_inmem-2022.5.16.dist-info/entry_points.txt
threatbus_inmem-2022.5.16.dist-info/top_level.txt
threatbus_inmem-2022.5.16.dist-info/RECORD
