Metadata-Version: 2.1
Name: threatbus-inmem
Version: 2022.5.16
Summary: A simplistic in-memory backbone for threatbus.
Home-page: https://github.com/tenzir/threatbus
Author: Tenzir
Author-email: engineering@tenzir.com
License: BSD 3-clause
Keywords: message broker,threatbus,Threat Bus,threat intelligence,TI,TI dissemination
Platform: UNKNOWN
Classifier: Development Status :: 4 - Beta
Classifier: Environment :: Plugins
Classifier: License :: OSI Approved :: BSD License
Classifier: Operating System :: MacOS :: MacOS X
Classifier: Operating System :: POSIX :: Linux
Classifier: Programming Language :: Python :: 3
Classifier: Topic :: Security
Classifier: Topic :: Software Development :: Object Brokering
Requires-Python: >=3.7
Requires-Dist: stix2 (>=3.0)
Requires-Dist: threatbus (>=2022.5.16)
